PascalsTriangle
