Metadata-Version: 2.1
Name: PascalsTriangle
Version: 0.2
Summary: Calculates the Pascals Triangle, up to a given depth
Home-page: https://github.com/urosjevremovic/PascalsTriangle
Author: Uros Jevremovic
Author-email: jevremovic.uros91@gmail.com
License: MIT
Platform: UNKNOWN
